[1,["c0QQvHDlJGT5P3iT9BrFPq","fb1hX9vxpEm4FMxHllZCo+@f9941","d8Svrlsb9MXZELUunTbF3M","edgI66r+VJmboVjtraWB0P@f9941","7dj5uJT9FMn6OrOOx83tfK@f9941","20g1ukYUVPvKWKBRznAKo+@f9941","54TknWPwVPqJqeCR+Y/Czo@f9941","95EkngnxZFbYuFpsqVTaFr@f9941","16q878VPVG9IX8Ls5zZ0aC@6c48a","20g1ukYUVPvKWKBRznAKo+@6c48a","20mVM9YpZMAaNrG7Yj7nfY@6c48a","e334E97+tPpotIGqtdu2C+@f9941","20mVM9YpZMAaNrG7Yj7nfY@f9941","95+UIBsRVEO41t/STcuZvB@f9941","85nFCy4D9I4Jf21fsP73ou@f9941","46PgWieG9HaauM4oj8mP4+@f9941","16q878VPVG9IX8Ls5zZ0aC@f9941","ffuIqPr2JI9I8dPLYGRDpD@f9941","d4X1RemQZEFqikSkv0pnAJ@f9941","3dfGbnCQRCG5PDPAwAuiom@f9941","6374gLCjNKPp0oNiR4ZUM4@f9941","f1MpC6cxNGB5U7Hwp6xRQk@f9941","36SDq4DQFKu4KYCTjrXWJd@f9941","9bNqICuPtKwZUbcH4EBbaF@f9941","e8YJMfa15FqaUpUZvlonA9@f9941","6a395FXTlP+pVxVQzF6Jdd@f9941","afxHkx8GZGsJC+n+YfITQo@f9941","36SDq4DQFKu4KYCTjrXWJd@6c48a","3dfGbnCQRCG5PDPAwAuiom@6c48a","46PgWieG9HaauM4oj8mP4+@6c48a","54TknWPwVPqJqeCR+Y/Czo@6c48a","6374gLCjNKPp0oNiR4ZUM4@6c48a","6a395FXTlP+pVxVQzF6Jdd@6c48a","7dj5uJT9FMn6OrOOx83tfK@6c48a","85nFCy4D9I4Jf21fsP73ou@6c48a","95EkngnxZFbYuFpsqVTaFr@6c48a","95+UIBsRVEO41t/STcuZvB@6c48a","9bNqICuPtKwZUbcH4EBbaF@6c48a","afxHkx8GZGsJC+n+YfITQo@6c48a","d4X1RemQZEFqikSkv0pnAJ@6c48a","e334E97+tPpotIGqtdu2C+@6c48a","e8YJMfa15FqaUpUZvlonA9@6c48a","edgI66r+VJmboVjtraWB0P@6c48a","f1MpC6cxNGB5U7Hwp6xRQk@6c48a","fb1hX9vxpEm4FMxHllZCo+@6c48a","ffuIqPr2JI9I8dPLYGRDpD@6c48a"],["node","_font","_spriteFrame","_textureSource","target","_parent","_target","_normalSprite","_hoverSprite","_pressedSprite","_disabledSprite","plantNode","plantSprite","_cameraComponent","speedValueLabel","hpValueLabel","scene","_scrollView"],["cc.SpriteFrame",["cc.Widget",["_alignFlags","_originalWidth","_left","_originalHeight","_right","_top","_bottom","_isAbsLeft","_isAbsRight","_isAbsTop","_isAbsBottom","node"],-8,1],["cc.Node",["_name","_layer","_active","_id","_objFlags","_components","_parent","_children","_lpos"],-2,9,1,2,5],["cc.Sprite",["_sizeMode","_type","_enabled","node","_spriteFrame","_color"],0,1,6,5],["cc.Label",["_string","_actualFontSize","_fontSize","_isSystemFontUsed","_overflow","_enableWrapText","_isBold","_lineHeight","node","_font","_color"],-5,1,6,5],["cc.Button",["_transition","node","_normalColor","_target","clickEvents","_normalSprite","_hoverSprite","_pressedSprite","_disabledSprite"],2,1,5,1,9,6,6,6,6],["cc.Node",["_name","_layer","_components","_lpos","_children","_parent"],1,12,5,2,1],["cc.UITransform",["node","_contentSize","_anchorPoint"],3,1,5,5],["cc.ClickEvent",["_componentId","handler","customEventData","target"],0,1],["cc.SceneAsset",["_name"],2],["cc.Node",["_name","_parent","_components","_lpos"],2,1,2,5],["5bb190TfD5GfYR0ZDuV9xuC",["node","plantNode"],3,1,1],["4f7b3Jpbt9JIozieLWDDBPm",["node","plantSprite","plantFrames"],3,1,1,3],["cc.Canvas",["node","_cameraComponent"],3,1,1],["cc.Layout",["_resizeMode","_layoutType","_spacingX","_isAlign","node"],-1,1],["3de62ad2pNEgYPcM6ogaDW5",["node","plantNode","bottomPanel"],3,1,1,1],["cc.BlockInputEvents",["node"],3,1],["cc.Mask",["node"],3,1],["cc.Graphics",["node","_fillColor"],3,1,5],["9ad55mNg3hOKKE7oF6tCjoa",["node","hpValueLabel","speedValueLabel","plantScrollView"],3,1,1,1,1],["a5dfc4LRidGD5KspyzQRndP",["node"],3,1],["cc.Scene",["_name","_children","_globals"],2,2,4],["cc.SceneGlobals",["ambient","shadows","_skybox","fog","octree","skin","lightProbeInfo","postSettings"],3,4,4,4,4,4,4,4,4],["cc.AmbientInfo",["_skyColorHDR","_groundAlbedoHDR"],3,5,5],["cc.ShadowsInfo",["_shadowColor","_size"],3,5,5],["cc.SkyboxInfo",[],3],["cc.FogInfo",[],3],["cc.OctreeInfo",[],3],["cc.SkinInfo",["_enabled"],2],["cc.LightProbeInfo",[],3],["cc.PostSettingsInfo",[],3],["cc.Camera",["_projection","_orthoHeight","_near","_far","_visibility","node","_color"],-2,1,5],["cc.ScrollBar",["_enableAutoHide","node","_handle"],2,1,1],["cc.ScrollView",["bounceDuration","brake","inertia","vertical","node","_content","_horizontalScrollBar"],-1,1,1,1],["cc.TTFFont",["_name","_native"],1]],[[7,0,1,1],[2,0,1,6,5,8,3],[4,0,1,2,7,3,8,10,9,6],[3,0,3,4,2],[7,0,1,2,1],[2,0,1,6,7,5,8,3],[2,0,1,6,5,3],[4,0,1,2,3,8,10,9,5],[2,0,2,1,6,5,8,4],[5,0,1,4,2],[8,0,1,2,3,4],[15,0,1,2,1],[2,0,4,1,6,5,4],[6,0,1,5,2,3,3],[1,0,1,11,3],[2,0,2,1,6,5,4],[7,0,1],[3,1,0,3,4,3],[2,0,1,7,5,8,3],[2,0,2,1,6,7,5,8,4],[1,0,1,3,11,4],[1,0,2,11,3],[5,0,1,2,3,2],[16,0,1],[4,0,1,2,4,5,3,8,9,7],[4,0,1,2,3,8,10,5],[34,0,1,3],[9,0,2],[2,0,1,3,7,5,8,4],[2,0,1,7,5,3],[2,0,1,6,7,5,3],[6,0,1,4,2,3,3],[6,0,1,5,4,2,3,3],[10,0,1,2,3,2],[1,0,2,4,5,6,7,8,9,10,1,3,11,12],[1,0,5,6,11,4],[1,0,11,2],[1,0,5,1,11,4],[1,0,6,11,3],[1,0,2,3,11,4],[1,0,7,8,9,10,1,3,11,8],[1,0,4,11,3],[1,0,2,4,1,11,5],[1,0,2,4,1,3,11,6],[11,0,1,1],[12,0,1,2,1],[13,0,1,1],[14,0,1,2,3,4,5],[5,0,1,4,2,3,5,6,7,8,2],[5,0,1,2,3,5,6,7,8,2],[5,0,1,2],[8,0,1,3,3],[3,2,1,0,3,4],[3,1,0,3,3],[3,1,0,3,5,4,3],[3,0,3,2],[3,1,0,3,5,3],[17,0,1],[18,0,1,1],[4,0,1,2,4,5,3,8,10,9,7],[4,0,1,2,4,5,3,6,8,9,8],[19,0,1,2,3,1],[20,0,1],[21,0,1,2,2],[22,0,1,2,3,4,5,6,7,1],[23,0,1,1],[24,0,1,1],[25,1],[26,1],[27,1],[28,0,2],[29,1],[30,1],[31,0,1,2,3,4,5,6,6],[32,0,1,2,2],[33,0,1,2,3,4,5,6,5]],[[[{"name":"plantviewbg","rect":{"x":0,"y":0,"width":3325,"height":1109},"offset":{"x":0,"y":0},"originalSize":{"width":3325,"height":1109},"rotated":false,"capInsets":[0,0,0,0],"vertices":{"rawPosition":[-1662.5,-554.5,0,1662.5,-554.5,0,-1662.5,554.5,0,1662.5,554.5,0],"indexes":[0,1,2,2,1,3],"uv":[0,1109,3325,1109,0,0,3325,0],"nuv":[0,0,1,0,0,1,1,1],"minPos":{"x":-1662.5,"y":-554.5,"z":0},"maxPos":{"x":1662.5,"y":554.5,"z":0}},"packable":true,"pixelsToUnit":100,"pivot":{"x":0.5,"y":0.5},"meshType":0}],[0],0,[0],[3],[8]],[[{"name":"default_btn_normal","rect":{"x":0,"y":0,"width":40,"height":40},"offset":{"x":0,"y":0},"originalSize":{"width":40,"height":40},"rotated":false,"capInsets":[12,12,12,12],"vertices":{"rawPosition":[-20,-20,0,20,-20,0,-20,20,0,20,20,0],"indexes":[0,1,2,2,1,3],"uv":[0,40,40,40,0,0,40,0],"nuv":[0,0,1,0,0,1,1,1],"minPos":{"x":-20,"y":-20,"z":0},"maxPos":{"x":20,"y":20,"z":0}},"packable":true,"pixelsToUnit":100,"pivot":{"x":0.5,"y":0.5},"meshType":0}],[0],0,[0],[3],[9]],[[{"name":"pothos_1","rect":{"x":92,"y":108,"width":159,"height":251},"offset":{"x":-8.5,"y":-53.5},"originalSize":{"width":360,"height":360},"rotated":false,"capInsets":[0,0,0,0],"vertices":{"rawPosition":[-79.5,-125.5,0,79.5,-125.5,0,-79.5,125.5,0,79.5,125.5,0],"indexes":[0,1,2,2,1,3],"uv":[92,252,251,252,92,1,251,1],"nuv":[0.25555555555555554,0.002777777777777778,0.6972222222222222,0.002777777777777778,0.25555555555555554,0.7,0.6972222222222222,0.7],"minPos":{"x":-79.5,"y":-125.5,"z":0},"maxPos":{"x":79.5,"y":125.5,"z":0}},"packable":true,"pixelsToUnit":100,"pivot":{"x":0.5,"y":0.5},"meshType":0}],[0],0,[0],[3],[10]],[[[27,"scene"],[18,"BottomPanel",33554432,[-5,-6,-7,-8,-9,-10,-11,-12,-13,-14,-15,-16,-17],[[0,-1,[5,600,100]],[14,44,100,-2],[44,-4,-3]],[1,0,-350,0]],[18,"PlantNode",33554432,[-22],[[0,-18,[5,360,360]],[34,45,0.2,0.2,0.09881916666666672,0.3011808333333333,false,false,false,false,100,500,-19],[45,-21,-20,[6,7,8]]],[1,0,60.70849999999996,0]],[28,"Canvas",33554432,"57Wh1tryBFFbrBsi/ml/CE",[-27,-28,-29,-30,1,-31,-32],[[0,-23,[5,600,800]],[46,-25,-24],[35,45,5.684341886080802e-14,5.684341886080802e-14,-26]],[1,300,400.00000000000006,0]],[29,"content",33554432,[-35,-36,-37,-38,-39,-40,-41],[[4,-33,[5,677,100],[0,0,0.5]],[47,1,1,2,true,-34]]],[5,"PothosIcon",33554432,4,[-46,-47,-48,-49,-50],[[0,-42,[5,95,95]],[9,3,-44,[[10,"3de62ad2pNEgYPcM6ogaDW5","onICONClick","绿萝",-43]]],[11,-45,2,1]],[1,47.5,0,0]],[5,"SucculentIcon",33554432,4,[-55,-56,-57,-58,-59],[[0,-51,[5,95,95]],[9,3,-53,[[10,"3de62ad2pNEgYPcM6ogaDW5","onICONClick","多肉",-52]]],[11,-54,2,1]],[1,144.5,0,0]],[5,"MintIcon",33554432,4,[-64,-65,-66,-67,-68],[[0,-60,[5,95,95]],[9,3,-62,[[10,"3de62ad2pNEgYPcM6ogaDW5","onICONClick","薄荷",-61]]],[11,-63,2,1]],[1,241.5,0,0]],[5,"LavenderIcon",33554432,4,[-73,-74,-75,-76,-77],[[0,-69,[5,95,95]],[9,3,-71,[[10,"3de62ad2pNEgYPcM6ogaDW5","onICONClick","薰衣草",-70]]],[11,-72,2,1]],[1,338.5,0,0]],[5,"SunflowerIcon",33554432,4,[-82,-83,-84,-85,-86],[[0,-78,[5,95,95]],[9,3,-80,[[10,"3de62ad2pNEgYPcM6ogaDW5","onICONClick","向日葵",-79]]],[11,-81,2,1]],[1,435.5,0,0]],[5,"DaisiesIcon",33554432,4,[-91,-92,-93,-94,-95],[[0,-87,[5,95,95]],[9,3,-89,[[10,"3de62ad2pNEgYPcM6ogaDW5","onICONClick","满天星",-88]]],[11,-90,2,1]],[1,532.5,0,0]],[5,"MagicflowIcon",33554432,4,[-100,-101,-102,-103,-104],[[0,-96,[5,95,95]],[9,3,-98,[[10,"3de62ad2pNEgYPcM6ogaDW5","onICONClick","魔法花",-97]]],[11,-99,2,1]],[1,629.5,0,0]],[31,"PlantScrollView",33554432,[-109,-110,-111],[[[0,-105,[5,600,100]],[52,false,1,0,-106],-107,[14,44,240,-108]],4,4,1,4],[1,0,-250,0]],[5,"TopPanel",33554432,3,[-114,-115,-116,-117,-118],[[0,-112,[5,600,100]],[14,41,100,-113]],[1,0,350,0]],[5,"hideButton",33554432,13,[-124],[[0,-119,[5,100,40]],[53,1,0,-120],[22,2,-122,[4,4292269782],-121],[36,32,-123]],[1,250,0,0]],[30,"CenterPanel",33554432,3,[-127,2,-128,12],[[0,-125,[5,600,600]],[37,41,100,100,-126]]],[5,"CareForButton",33554432,15,[-134],[[0,-129,[5,150,60]],[17,1,0,-130,10],[22,3,-132,[4,4292269782],-131],[38,4,109.112,-133]],[1,0,-160.888,0]],[19,"upgradeButton",false,33554432,1,[-140],[[0,-135,[5,100,40]],[17,1,0,-136,20],[48,3,-138,[[51,"5bb190TfD5GfYR0ZDuV9xuC","onUpgradeClick",1]],[4,4292269782],-137,21,22,23,24],[23,-139]],[1,157.247,0,0]],[19,"unlockButton",false,33554432,1,[-146],[[0,-141,[5,100,40]],[17,1,0,-142,36],[49,3,-144,[4,4292269782],-143,37,38,39,40],[23,-145]],[1,141.403,3.97,0]],[5,"view",33554432,12,[4],[[4,-147,[5,600,100],[0,0,0.5]],[57,-148],[58,-149,[4,16777215]],[14,44,240,-150]],[1,-300,0,0]],[5,"HpBox",33554432,13,[-153,-154],[[16,-151],[39,13,20,100,-152]],[1,-230,0,0]],[32,"scrollBar",33554432,12,[-158],[[[4,-155,[5,600,10],[0,0,0]],[54,1,0,-156,[4,16777215],12],-157],4,4,1],[1,-300,-50,0]],[6,"Backgroud",33554432,3,[[0,-159,[5,600,800]],[3,0,-160,0],[20,45,600,800,-161]]],[15,"Bg",false,33554432,13,[[0,-162,[5,600,100]],[3,0,-163,1],[40,45,false,false,false,false,2,2,-164]]],[6,"HpLabel",33554432,20,[[0,-165,[5,99.97041703209626,50.400000000000006]],[7,"生命能量：",25.3875,20,false,-166,[4,4278190080],2],[21,8,0.01479148395186769,-167]]],[13,"HpValueLabel",33554432,20,[[[4,-168,[5,71.07894048498277,50.400000000000006],[0,0,0.5]],-169,[21,8,104.26113401813271,-170]],4,1,4],[1,54.26113401813271,0,0]],[1,"SpeedLabel",33554432,13,[[0,-171,[5,27.452813904018956,50.400000000000006]],[7,"⚡️",25.3875,20,false,-172,[4,4278190080],3],[41,32,199.3058196104905,-173]],[1,86.96777343750003,0,0]],[13,"SpeedValueLabel",33554432,13,[[[4,-174,[5,68.71964770664083,50.400000000000006],[0,0,0.5]],-175,[42,32,269.697265625,125.94968340832827,60.60546875,-176]],4,1,4],[1,105.3306688850309,0,0]],[15,"Bg",false,33554432,15,[[0,-177,[5,600,600]],[3,0,-178,5],[20,45,2,2,-179]]],[13,"PlantSprite",33554432,2,[[[0,-180,[5,150,150]],-181,[50,3,-182]],4,1,4],[1,0,-117.778,0]],[15,"Bg",false,33554432,1,[[0,-183,[5,450,100]],[3,0,-184,18],[43,45,75,75,2,2,-185]]],[12,"Label",512,33554432,14,[[0,-186,[5,100,40]],[59,"📋",25.3875,20,1,false,false,-187,[4,4278190080],4]]],[12,"Label",512,33554432,16,[[0,-188,[5,100,40]],[60,"点击照料",31.734374999999996,25,1,false,false,true,-189,9]]],[6,"Bg",33554432,12,[[0,-190,[5,600,100]],[3,0,-191,11]]],[13,"bar",33554432,21,[[[4,-192,[5,600,10],[0,0,0]],-193],4,1],[1,-11,-31.25,0]],[6,"Bg",33554432,5,[[0,-194,[5,85,85]],[3,0,-195,13]]],[1,"PlantIcon",33554432,5,[[0,-196,[5,80,60]],[3,0,-197,14]],[1,-0.136,12.366,0]],[1,"NameLabel",33554432,5,[[0,-198,[5,25.99704579025111,16.38]],[2,"绿萝",16.501875,13,13,false,-199,[4,4278190080],15]],[1,-26.282,-23.345,0]],[1,"LevelLabel",33554432,5,[[4,-200,[5,25.880048217472922,16.38],[0,0,0.5]],[2,"lv.3",16.501875,13,13,false,-201,[4,4278190080],16]],[1,-38.459,-37.057,0]],[1,"SpeedLabel",33554432,5,[[0,-202,[5,29.857581029203597,16.38]],[2,"30/s",16.501875,13,13,false,-203,[4,4278190080],17]],[1,26.675,-34.09,0]],[12,"Label",512,33554432,17,[[0,-204,[5,100,40]],[24,"升级",25.3875,20,1,false,false,-205,19]]],[8,"plantNameLabel",false,33554432,1,[[0,-206,[5,64.8428484467319,50.400000000000006]],[7,"植物名称：",19.040625,15,false,-207,[4,4281952829],25]],[1,-171.787,23.13,0]],[8,"plantNameValueLabel",false,33554432,1,[[0,-208,[5,29.999004685192027,50.400000000000006]],[7,"绿萝",19.040625,15,false,-209,[4,4281952829],26]],[1,-114.324,23.452,0]],[8,"levelLabel",false,33554432,1,[[0,-210,[5,64.8428484467319,50.400000000000006]],[7,"当前等级：",19.040625,15,false,-211,[4,4281952829],27]],[1,-173.684,-5.282,0]],[8,"levelValueLabel",false,33554432,1,[[0,-212,[5,29.23403072685869,50.400000000000006]],[7,"10级",19.040625,15,false,-213,[4,4281952829],28]],[1,-110.711,-5.604,0]],[8,"nextLevelLabel",false,33554432,1,[[0,-214,[5,94.84185313192394,50.400000000000006]],[7,"升级所需能量：",19.040625,15,false,-215,[4,4281952829],29]],[1,-157.433,-30.571,0]],[8,"nextLevelValueLabel",false,33554432,1,[[4,-216,[5,26.489125584687347,50.400000000000006],[0,0,0.5]],[7,"200",19.040625,15,false,-217,[4,4281952829],30]],[1,-92.428,-29.607,0]],[8,"unlockLabel",false,33554432,1,[[0,-218,[5,145.27017507924054,50.400000000000006]],[7,"未解锁，解锁所需种子：",19.040625,15,false,-219,[4,4281952829],31]],[1,-139.075,4.671,0]],[8,"unlockSeedNameLabel",false,33554432,1,[[4,-220,[5,29.999004685192027,50.400000000000006],[0,0,0.5]],[7,"绿萝",19.040625,15,false,-221,[4,4281952829],32]],[1,-59.203,3.837,0]],[8,"unlockSeedCountLabel",false,33554432,1,[[4,-222,[5,7.077902376446333,50.400000000000006],[0,0,0.5]],[7,"1",25.3875,20,false,-223,[4,4281952829],33]],[1,-12.478,4.688,0]],[8,"unlockSeedUnitLabel",false,33554432,1,[[0,-224,[5,14.999502342596013,50.400000000000006]],[7,"个",19.040625,15,false,-225,[4,4281952829],34]],[1,9.144,5.254,0]],[12,"Label",512,33554432,18,[[0,-226,[5,100,40]],[24,"立即解锁",25.3875,20,1,false,false,-227,35]]],[6,"Bg",33554432,6,[[0,-228,[5,85,85]],[3,0,-229,41]]],[1,"PlantIcon",33554432,6,[[0,-230,[5,76.416,57.126]],[3,0,-231,42]],[1,-0.251,10.929,0]],[1,"NameLabel",33554432,6,[[0,-232,[5,25.99704579025111,16.38]],[2,"多肉",16.501875,13,13,false,-233,[4,4278190080],43]],[1,-26.282,-23.345,0]],[1,"LevelLabel",33554432,6,[[4,-234,[5,25.880048217472922,16.38],[0,0,0.5]],[2,"lv.3",16.501875,13,13,false,-235,[4,4278190080],44]],[1,-38.459,-37.057,0]],[1,"SpeedLabel",33554432,6,[[0,-236,[5,29.857581029203597,16.38]],[2,"30/s",16.501875,13,13,false,-237,[4,4278190080],45]],[1,26.675,-34.09,0]],[6,"Bg",33554432,7,[[0,-238,[5,85,85]],[3,0,-239,46]]],[1,"PlantIcon",33554432,7,[[0,-240,[5,79.052,60]],[3,0,-241,47]],[1,1.067,12.366,0]],[1,"NameLabel",33554432,7,[[0,-242,[5,25.99704579025111,16.38]],[2,"薄荷",16.501875,13,13,false,-243,[4,4278190080],48]],[1,-26.282,-23.345,0]],[1,"LevelLabel",33554432,7,[[4,-244,[5,25.880048217472922,16.38],[0,0,0.5]],[2,"lv.3",16.501875,13,13,false,-245,[4,4278190080],49]],[1,-38.459,-37.057,0]],[1,"SpeedLabel",33554432,7,[[0,-246,[5,29.857581029203597,16.38]],[2,"30/s",16.501875,13,13,false,-247,[4,4278190080],50]],[1,26.675,-34.09,0]],[6,"Bg",33554432,8,[[0,-248,[5,85,85]],[3,0,-249,51]]],[1,"PlantIcon",33554432,8,[[0,-250,[5,80.41,55.137]],[3,0,-251,52]],[1,1.067,12.366,0]],[1,"NameLabel",33554432,8,[[0,-252,[5,38.99556868537666,16.38]],[2,"薰衣草",16.501875,13,13,false,-253,[4,4278190080],53]],[1,-21.567,-23.345,0]],[1,"LevelLabel",33554432,8,[[4,-254,[5,25.880048217472922,16.38],[0,0,0.5]],[2,"lv.3",16.501875,13,13,false,-255,[4,4278190080],54]],[1,-38.459,-37.057,0]],[1,"SpeedLabel",33554432,8,[[0,-256,[5,29.857581029203597,16.38]],[2,"30/s",16.501875,13,13,false,-257,[4,4278190080],55]],[1,25.067,-34.09,0]],[6,"Bg",33554432,9,[[0,-258,[5,85,85]],[3,0,-259,56]]],[1,"PlantIcon",33554432,9,[[0,-260,[5,85.32900000000001,60]],[3,0,-261,57]],[1,0,12.499999999999943,0]],[1,"NameLabel",33554432,9,[[0,-262,[5,38.99556868537666,16.38]],[2,"向日葵",16.501875,13,13,false,-263,[4,4278190080],58]],[1,-21.567,-23.345,0]],[1,"LevelLabel",33554432,9,[[4,-264,[5,25.880048217472922,16.38],[0,0,0.5]],[2,"lv.3",16.501875,13,13,false,-265,[4,4278190080],59]],[1,-38.459,-37.057,0]],[1,"SpeedLabel",33554432,9,[[0,-266,[5,29.857581029203597,16.38]],[2,"30/s",16.501875,13,13,false,-267,[4,4278190080],60]],[1,25.067,-34.09,0]],[6,"Bg",33554432,10,[[0,-268,[5,85,85]],[3,0,-269,61]]],[1,"PlantIcon",33554432,10,[[0,-270,[5,80.3,53.5]],[3,0,-271,62]],[1,-2.3505,15.75,0]],[1,"NameLabel",33554432,10,[[0,-272,[5,38.99556868537666,16.38]],[2,"满天星",16.501875,13,13,false,-273,[4,4278190080],63]],[1,-21.503,-23.345,0]],[1,"LevelLabel",33554432,10,[[4,-274,[5,25.880048217472922,16.38],[0,0,0.5]],[2,"lv.3",16.501875,13,13,false,-275,[4,4278190080],64]],[1,-38.459,-37.057,0]],[1,"SpeedLabel",33554432,10,[[0,-276,[5,29.857581029203597,16.38]],[2,"30/s",16.501875,13,13,false,-277,[4,4278190080],65]],[1,25.067,-34.09,0]],[6,"Bg",33554432,11,[[0,-278,[5,85,85]],[3,0,-279,66]]],[1,"PlantIcon",33554432,11,[[0,-280,[5,75.523,58.453]],[3,0,-281,67]],[1,-2.666,18.227,0]],[1,"NameLabel",33554432,11,[[0,-282,[5,38.99556868537666,16.38]],[2,"魔法花",16.501875,13,13,false,-283,[4,4278190080],68]],[1,-20.231,-23.345,0]],[1,"LevelLabel",33554432,11,[[4,-284,[5,25.880048217472922,16.38],[0,0,0.5]],[2,"lv.3",16.501875,13,13,false,-285,[4,4278190080],69]],[1,-38.459,-37.057,0]],[1,"SpeedLabel",33554432,11,[[0,-286,[5,29.857581029203597,16.38]],[2,"30/s",16.501875,13,13,false,-287,[4,4278190080],70]],[1,25.067,-34.09,0]],[6,"GameManager",33554432,3,[[16,-288],[61,-291,-290,-289,12]]],[6,"DataManager",33554432,3,[[16,-292],[62,-293]]],[63,"scene",[3],[64,[65,[2,0,0,0,0.520833125],[2,0,0,0,0]],[66,[4,4283190348],[0,512,512]],[67],[68],[69],[70,false],[71],[72]]],[33,"Camera",3,[-294],[1,0,0,1000]],[73,0,400,0,2000,1108344832,85,[4,4278190080]],[25,"12345",25.3875,20,false,25,[4,4278190080]],[25,"+123/s",25.3875,20,false,27,[4,4278190080]],[55,0,29],[56,1,0,34,[4,16777215]],[74,true,21,90],[75,0.23,0.75,false,false,12,4,91]],0,[0,0,1,0,0,1,0,11,2,0,0,1,0,-1,30,0,-2,17,0,-3,41,0,-4,42,0,-5,43,0,-6,44,0,-7,45,0,-8,46,0,-9,47,0,-10,48,0,-11,49,0,-12,50,0,-13,18,0,0,2,0,0,2,0,12,89,0,0,2,0,-1,29,0,0,3,0,13,86,0,0,3,0,0,3,0,-1,85,0,-2,22,0,-3,13,0,-4,15,0,-6,82,0,-7,83,0,0,4,0,0,4,0,-1,5,0,-2,6,0,-3,7,0,-4,8,0,-5,9,0,-6,10,0,-7,11,0,0,5,0,4,5,0,0,5,0,0,5,0,-1,35,0,-2,36,0,-3,37,0,-4,38,0,-5,39,0,0,6,0,4,6,0,0,6,0,0,6,0,-1,52,0,-2,53,0,-3,54,0,-4,55,0,-5,56,0,0,7,0,4,7,0,0,7,0,0,7,0,-1,57,0,-2,58,0,-3,59,0,-4,60,0,-5,61,0,0,8,0,4,8,0,0,8,0,0,8,0,-1,62,0,-2,63,0,-3,64,0,-4,65,0,-5,66,0,0,9,0,4,9,0,0,9,0,0,9,0,-1,67,0,-2,68,0,-3,69,0,-4,70,0,-5,71,0,0,10,0,4,10,0,0,10,0,0,10,0,-1,72,0,-2,73,0,-3,74,0,-4,75,0,-5,76,0,0,11,0,4,11,0,0,11,0,0,11,0,-1,77,0,-2,78,0,-3,79,0,-4,80,0,-5,81,0,0,12,0,0,12,0,-3,92,0,0,12,0,-1,33,0,-2,21,0,-3,19,0,0,13,0,0,13,0,-1,23,0,-2,20,0,-3,26,0,-4,27,0,-5,14,0,0,14,0,0,14,0,6,14,0,0,14,0,0,14,0,-1,31,0,0,15,0,0,15,0,-1,28,0,-3,16,0,0,16,0,0,16,0,6,16,0,0,16,0,0,16,0,-1,32,0,0,17,0,0,17,0,6,17,0,0,17,0,0,17,0,-1,40,0,0,18,0,0,18,0,6,18,0,0,18,0,0,18,0,-1,51,0,0,19,0,0,19,0,0,19,0,0,19,0,0,20,0,0,20,0,-1,24,0,-2,25,0,0,21,0,0,21,0,-3,91,0,-1,34,0,0,22,0,0,22,0,0,22,0,0,23,0,0,23,0,0,23,0,0,24,0,0,24,0,0,24,0,0,25,0,-2,87,0,0,25,0,0,26,0,0,26,0,0,26,0,0,27,0,-2,88,0,0,27,0,0,28,0,0,28,0,0,28,0,0,29,0,-2,89,0,0,29,0,0,30,0,0,30,0,0,30,0,0,31,0,0,31,0,0,32,0,0,32,0,0,33,0,0,33,0,0,34,0,-2,90,0,0,35,0,0,35,0,0,36,0,0,36,0,0,37,0,0,37,0,0,38,0,0,38,0,0,39,0,0,39,0,0,40,0,0,40,0,0,41,0,0,41,0,0,42,0,0,42,0,0,43,0,0,43,0,0,44,0,0,44,0,0,45,0,0,45,0,0,46,0,0,46,0,0,47,0,0,47,0,0,48,0,0,48,0,0,49,0,0,49,0,0,50,0,0,50,0,0,51,0,0,51,0,0,52,0,0,52,0,0,53,0,0,53,0,0,54,0,0,54,0,0,55,0,0,55,0,0,56,0,0,56,0,0,57,0,0,57,0,0,58,0,0,58,0,0,59,0,0,59,0,0,60,0,0,60,0,0,61,0,0,61,0,0,62,0,0,62,0,0,63,0,0,63,0,0,64,0,0,64,0,0,65,0,0,65,0,0,66,0,0,66,0,0,67,0,0,67,0,0,68,0,0,68,0,0,69,0,0,69,0,0,70,0,0,70,0,0,71,0,0,71,0,0,72,0,0,72,0,0,73,0,0,73,0,0,74,0,0,74,0,0,75,0,0,75,0,0,76,0,0,76,0,0,77,0,0,77,0,0,78,0,0,78,0,0,79,0,0,79,0,0,80,0,0,80,0,0,81,0,0,81,0,0,82,0,14,88,0,15,87,0,0,82,0,0,83,0,0,83,0,-1,86,0,16,84,1,5,3,2,5,15,3,5,84,4,5,19,12,5,15,91,17,92,294],[0,0,0,0,0,0,0,0,0,0,0,0,0,0,0,0,0,0,0,0,0,0,0,0,0,0,0,0,0,0,0,0,0,0,0,0,0,0,0,0,0,0,0,0,0,0,0,0,0,0,0,0,0,0,0,0,0,0,0,0,0,0,0,0,0,0,0,0,0,0,0,87,88,90],[2,2,1,1,1,2,-1,-2,-3,1,2,2,2,2,2,1,1,1,2,1,2,7,8,9,10,1,1,1,1,1,1,1,1,1,1,1,2,7,8,9,10,2,2,1,1,1,2,2,1,1,1,2,2,1,1,1,2,2,1,1,1,2,2,1,1,1,2,2,1,1,1,1,1,2],[11,4,2,2,2,4,12,13,14,0,15,16,17,1,18,0,0,0,19,0,3,3,5,6,7,0,0,0,0,0,0,0,0,0,0,0,3,3,5,6,7,1,20,0,0,0,1,21,0,0,0,1,22,0,0,0,1,23,0,0,0,1,24,0,0,0,1,25,0,0,0,2,2,26]],[[{"name":"lavender-icon","rect":{"x":242,"y":43,"width":150,"height":304},"offset":{"x":-5.5,"y":-1.5},"originalSize":{"width":645,"height":387},"rotated":false,"capInsets":[0,0,0,0],"vertices":{"rawPosition":[-75,-152,0,75,-152,0,-75,152,0,75,152,0],"indexes":[0,1,2,2,1,3],"uv":[242,344,392,344,242,40,392,40],"nuv":[0.3751937984496124,0.10335917312661498,0.6077519379844961,0.10335917312661498,0.3751937984496124,0.8888888888888888,0.6077519379844961,0.8888888888888888],"minPos":{"x":-75,"y":-152,"z":0},"maxPos":{"x":75,"y":152,"z":0}},"packable":true,"pixelsToUnit":100,"pivot":{"x":0.5,"y":0.5},"meshType":0}],[0],0,[0],[3],[27]],[[{"name":"bottombg","rect":{"x":0,"y":0,"width":63,"height":53},"offset":{"x":0,"y":0},"originalSize":{"width":63,"height":53},"rotated":false,"capInsets":[0,0,0,0],"vertices":{"rawPosition":[-31.5,-26.5,0,31.5,-26.5,0,-31.5,26.5,0,31.5,26.5,0],"indexes":[0,1,2,2,1,3],"uv":[0,53,63,53,0,0,63,0],"nuv":[0,0,1,0,0,1,1,1],"minPos":{"x":-31.5,"y":-26.5,"z":0},"maxPos":{"x":31.5,"y":26.5,"z":0}},"packable":true,"pixelsToUnit":100,"pivot":{"x":0.5,"y":0.5},"meshType":0}],[0],0,[0],[3],[28]],[[{"name":"greenbuttonbg","rect":{"x":0,"y":0,"width":428,"height":162},"offset":{"x":0,"y":0},"originalSize":{"width":428,"height":162},"rotated":false,"capInsets":[0,0,0,0],"vertices":{"rawPosition":[-214,-81,0,214,-81,0,-214,81,0,214,81,0],"indexes":[0,1,2,2,1,3],"uv":[0,162,428,162,0,0,428,0],"nuv":[0,0,1,0,0,1,1,1],"minPos":{"x":-214,"y":-81,"z":0},"maxPos":{"x":214,"y":81,"z":0}},"packable":true,"pixelsToUnit":100,"pivot":{"x":0.5,"y":0.5},"meshType":0}],[0],0,[0],[3],[29]],[[{"name":"default_btn_pressed","rect":{"x":0,"y":0,"width":40,"height":40},"offset":{"x":0,"y":0},"originalSize":{"width":40,"height":40},"rotated":false,"capInsets":[12,12,12,12],"vertices":{"rawPosition":[-20,-20,0,20,-20,0,-20,20,0,20,20,0],"indexes":[0,1,2,2,1,3],"uv":[0,40,40,40,0,0,40,0],"nuv":[0,0,1,0,0,1,1,1],"minPos":{"x":-20,"y":-20,"z":0},"maxPos":{"x":20,"y":20,"z":0}},"packable":true,"pixelsToUnit":100,"pivot":{"x":0.5,"y":0.5},"meshType":0}],[0],0,[0],[3],[30]],[[{"name":"succulent-icon","rect":{"x":170,"y":63,"width":305,"height":261},"offset":{"x":0,"y":0},"originalSize":{"width":645,"height":387},"rotated":false,"capInsets":[0,0,0,0],"vertices":{"rawPosition":[-152.5,-130.5,0,152.5,-130.5,0,-152.5,130.5,0,152.5,130.5,0],"indexes":[0,1,2,2,1,3],"uv":[170,324,475,324,170,63,475,63],"nuv":[0.26356589147286824,0.16279069767441862,0.7364341085271318,0.16279069767441862,0.26356589147286824,0.8372093023255814,0.7364341085271318,0.8372093023255814],"minPos":{"x":-152.5,"y":-130.5,"z":0},"maxPos":{"x":152.5,"y":130.5,"z":0}},"packable":true,"pixelsToUnit":100,"pivot":{"x":0.5,"y":0.5},"meshType":0}],[0],0,[0],[3],[31]],[[{"name":"Magicflower-icon","rect":{"x":172,"y":14,"width":301,"height":360},"offset":{"x":0,"y":-0.5},"originalSize":{"width":645,"height":387},"rotated":false,"capInsets":[0,0,0,0],"vertices":{"rawPosition":[-150.5,-180,0,150.5,-180,0,-150.5,180,0,150.5,180,0],"indexes":[0,1,2,2,1,3],"uv":[172,373,473,373,172,13,473,13],"nuv":[0.26666666666666666,0.03359173126614987,0.7333333333333333,0.03359173126614987,0.26666666666666666,0.9638242894056848,0.7333333333333333,0.9638242894056848],"minPos":{"x":-150.5,"y":-180,"z":0},"maxPos":{"x":150.5,"y":180,"z":0}},"packable":true,"pixelsToUnit":100,"pivot":{"x":0.5,"y":0.5},"meshType":0}],[0],0,[0],[3],[32]],[[{"name":"default_sprite_splash","rect":{"x":0,"y":0,"width":2,"height":2},"offset":{"x":0,"y":0},"originalSize":{"width":2,"height":2},"rotated":false,"capInsets":[0,0,0,0],"vertices":{"rawPosition":[-1,-1,0,1,-1,0,-1,1,0,1,1,0],"indexes":[0,1,2,2,1,3],"uv":[0,2,2,2,0,0,2,0],"nuv":[0,0,1,0,0,1,1,1],"minPos":{"x":-1,"y":-1,"z":0},"maxPos":{"x":1,"y":1,"z":0}},"packable":true,"pixelsToUnit":100,"pivot":{"x":0.5,"y":0.5},"meshType":0}],[0],0,[0],[3],[33]],[[{"name":"pothos_3","rect":{"x":62,"y":62,"width":223,"height":298},"offset":{"x":-6.5,"y":-31},"originalSize":{"width":360,"height":360},"rotated":false,"capInsets":[0,0,0,0],"vertices":{"rawPosition":[-111.5,-149,0,111.5,-149,0,-111.5,149,0,111.5,149,0],"indexes":[0,1,2,2,1,3],"uv":[62,298,285,298,62,0,285,0],"nuv":[0.17222222222222222,0,0.7916666666666666,0,0.17222222222222222,0.8277777777777777,0.7916666666666666,0.8277777777777777],"minPos":{"x":-111.5,"y":-149,"z":0},"maxPos":{"x":111.5,"y":149,"z":0}},"packable":true,"pixelsToUnit":100,"pivot":{"x":0.5,"y":0.5},"meshType":0}],[0],0,[0],[3],[34]],[[{"name":"default_btn_disabled","rect":{"x":0,"y":0,"width":40,"height":40},"offset":{"x":0,"y":0},"originalSize":{"width":40,"height":40},"rotated":false,"capInsets":[12,12,12,12],"vertices":{"rawPosition":[-20,-20,0,20,-20,0,-20,20,0,20,20,0],"indexes":[0,1,2,2,1,3],"uv":[0,40,40,40,0,0,40,0],"nuv":[0,0,1,0,0,1,1,1],"minPos":{"x":-20,"y":-20,"z":0},"maxPos":{"x":20,"y":20,"z":0}},"packable":true,"pixelsToUnit":100,"pivot":{"x":0.5,"y":0.5},"meshType":0}],[0],0,[0],[3],[35]],[[{"name":"pothos_2","rect":{"x":85,"y":87,"width":187,"height":273},"offset":{"x":-1.5,"y":-43.5},"originalSize":{"width":360,"height":360},"rotated":false,"capInsets":[0,0,0,0],"vertices":{"rawPosition":[-93.5,-136.5,0,93.5,-136.5,0,-93.5,136.5,0,93.5,136.5,0],"indexes":[0,1,2,2,1,3],"uv":[85,273,272,273,85,0,272,0],"nuv":[0.2361111111111111,0,0.7555555555555555,0,0.2361111111111111,0.7583333333333333,0.7555555555555555,0.7583333333333333],"minPos":{"x":-93.5,"y":-136.5,"z":0},"maxPos":{"x":93.5,"y":136.5,"z":0}},"packable":true,"pixelsToUnit":100,"pivot":{"x":0.5,"y":0.5},"meshType":0}],[0],0,[0],[3],[36]],[[{"name":"sunflower-icon","rect":{"x":141,"y":9,"width":363,"height":368},"offset":{"x":0,"y":0.5},"originalSize":{"width":645,"height":387},"rotated":false,"capInsets":[0,0,0,0],"vertices":{"rawPosition":[-181.5,-184,0,181.5,-184,0,-181.5,184,0,181.5,184,0],"indexes":[0,1,2,2,1,3],"uv":[141,378,504,378,141,10,504,10],"nuv":[0.2186046511627907,0.025839793281653745,0.7813953488372093,0.025839793281653745,0.2186046511627907,0.9767441860465116,0.7813953488372093,0.9767441860465116],"minPos":{"x":-181.5,"y":-184,"z":0},"maxPos":{"x":181.5,"y":184,"z":0}},"packable":true,"pixelsToUnit":100,"pivot":{"x":0.5,"y":0.5},"meshType":0}],[0],0,[0],[3],[37]],[[{"name":"default_scrollbar_vertical","rect":{"x":0,"y":0,"width":15,"height":30},"offset":{"x":0,"y":0},"originalSize":{"width":15,"height":30},"rotated":false,"capInsets":[4,10,4,10],"vertices":{"rawPosition":[-7.5,-15,0,7.5,-15,0,-7.5,15,0,7.5,15,0],"indexes":[0,1,2,2,1,3],"uv":[0,30,15,30,0,0,15,0],"nuv":[0,0,1,0,0,1,1,1],"minPos":{"x":-7.5,"y":-15,"z":0},"maxPos":{"x":7.5,"y":15,"z":0}},"packable":true,"pixelsToUnit":100,"pivot":{"x":0.5,"y":0.5},"meshType":0}],[0],0,[0],[3],[38]],[[[26,"LemiBoBoTi","LemiBoBoTi.ttf"],-1],0,0,[],[],[]],[[{"name":"pothos-icon","rect":{"x":188,"y":58,"width":269,"height":274},"offset":{"x":0,"y":-1.5},"originalSize":{"width":645,"height":387},"rotated":false,"capInsets":[0,0,0,0],"vertices":{"rawPosition":[-134.5,-137,0,134.5,-137,0,-134.5,137,0,134.5,137,0],"indexes":[0,1,2,2,1,3],"uv":[188,329,457,329,188,55,457,55],"nuv":[0.29147286821705426,0.1421188630490956,0.7085271317829457,0.1421188630490956,0.29147286821705426,0.8501291989664083,0.7085271317829457,0.8501291989664083],"minPos":{"x":-134.5,"y":-137,"z":0},"maxPos":{"x":134.5,"y":137,"z":0}},"packable":true,"pixelsToUnit":100,"pivot":{"x":0.5,"y":0.5},"meshType":0}],[0],0,[0],[3],[39]],[[[26,"DymonShouXieTi","DymonShouXieTi.ttf"],-1],0,0,[],[],[]],[[{"name":"bg","rect":{"x":0,"y":0,"width":540,"height":720},"offset":{"x":0,"y":0},"originalSize":{"width":540,"height":720},"rotated":false,"capInsets":[0,0,0,0],"vertices":{"rawPosition":[-270,-360,0,270,-360,0,-270,360,0,270,360,0],"indexes":[0,1,2,2,1,3],"uv":[0,720,540,720,0,0,540,0],"nuv":[0,0,1,0,0,1,1,1],"minPos":{"x":-270,"y":-360,"z":0},"maxPos":{"x":270,"y":360,"z":0}},"packable":true,"pixelsToUnit":100,"pivot":{"x":0.5,"y":0.5},"meshType":0}],[0],0,[0],[3],[40]],[[{"name":"Daisies-icon","rect":{"x":165,"y":24,"width":317,"height":341},"offset":{"x":1,"y":-1},"originalSize":{"width":645,"height":387},"rotated":false,"capInsets":[0,0,0,0],"vertices":{"rawPosition":[-158.5,-170.5,0,158.5,-170.5,0,-158.5,170.5,0,158.5,170.5,0],"indexes":[0,1,2,2,1,3],"uv":[165,363,482,363,165,22,482,22],"nuv":[0.2558139534883721,0.056847545219638244,0.7472868217054264,0.056847545219638244,0.2558139534883721,0.937984496124031,0.7472868217054264,0.937984496124031],"minPos":{"x":-158.5,"y":-170.5,"z":0},"maxPos":{"x":158.5,"y":170.5,"z":0}},"packable":true,"pixelsToUnit":100,"pivot":{"x":0.5,"y":0.5},"meshType":0}],[0],0,[0],[3],[41]],[[{"name":"upgradelevelbutton","rect":{"x":0,"y":0,"width":145,"height":117},"offset":{"x":0,"y":0},"originalSize":{"width":145,"height":117},"rotated":false,"capInsets":[0,0,0,0],"vertices":{"rawPosition":[-72.5,-58.5,0,72.5,-58.5,0,-72.5,58.5,0,72.5,58.5,0],"indexes":[0,1,2,2,1,3],"uv":[0,117,145,117,0,0,145,0],"nuv":[0,0,1,0,0,1,1,1],"minPos":{"x":-72.5,"y":-58.5,"z":0},"maxPos":{"x":72.5,"y":58.5,"z":0}},"packable":true,"pixelsToUnit":100,"pivot":{"x":0.5,"y":0.5},"meshType":0}],[0],0,[0],[3],[42]],[[{"name":"mint-icon","rect":{"x":204,"y":36,"width":241,"height":314},"offset":{"x":2,"y":0.5},"originalSize":{"width":645,"height":387},"rotated":false,"capInsets":[0,0,0,0],"vertices":{"rawPosition":[-120.5,-157,0,120.5,-157,0,-120.5,157,0,120.5,157,0],"indexes":[0,1,2,2,1,3],"uv":[204,351,445,351,204,37,445,37],"nuv":[0.31627906976744186,0.09560723514211886,0.689922480620155,0.09560723514211886,0.31627906976744186,0.9069767441860465,0.689922480620155,0.9069767441860465],"minPos":{"x":-120.5,"y":-157,"z":0},"maxPos":{"x":120.5,"y":157,"z":0}},"packable":true,"pixelsToUnit":100,"pivot":{"x":0.5,"y":0.5},"meshType":0}],[0],0,[0],[3],[43]],[[{"name":"plantgzbg","rect":{"x":0,"y":0,"width":2048,"height":2048},"offset":{"x":0,"y":0},"originalSize":{"width":2048,"height":2048},"rotated":false,"capInsets":[0,0,0,0],"vertices":{"rawPosition":[-1024,-1024,0,1024,-1024,0,-1024,1024,0,1024,1024,0],"indexes":[0,1,2,2,1,3],"uv":[0,2048,2048,2048,0,0,2048,0],"nuv":[0,0,1,0,0,1,1,1],"minPos":{"x":-1024,"y":-1024,"z":0},"maxPos":{"x":1024,"y":1024,"z":0}},"packable":true,"pixelsToUnit":100,"pivot":{"x":0.5,"y":0.5},"meshType":0}],[0],0,[0],[3],[44]],[[{"name":"default_scrollbar_vertical_bg","rect":{"x":0,"y":0,"width":15,"height":30},"offset":{"x":0,"y":0},"originalSize":{"width":15,"height":30},"rotated":false,"capInsets":[4,10,4,10],"vertices":{"rawPosition":[-7.5,-15,0,7.5,-15,0,-7.5,15,0,7.5,15,0],"indexes":[0,1,2,2,1,3],"uv":[0,30,15,30,0,0,15,0],"nuv":[0,0,1,0,0,1,1,1],"minPos":{"x":-7.5,"y":-15,"z":0},"maxPos":{"x":7.5,"y":15,"z":0}},"packable":true,"pixelsToUnit":100,"pivot":{"x":0.5,"y":0.5},"meshType":0}],[0],0,[0],[3],[45]]]]
